morphine/__init__.py
morphine/globals.py
morphine/minimal.py
morphine/minimal_deps.py
morphine/minimal_exec.py
morphine/minimal_exec_deps.py
morphine/startup.py
morphine/template.py
morphine_maker-2.0.2.dist-info/METADATA
morphine_maker-2.0.2.dist-info/RECORD
morphine_maker-2.0.2.dist-info/WHEEL
morphine_maker-2.0.2.dist-info/entry_points.txt
morphine_maker-2.0.2.dist-info/top_level.txt
