Metadata-Version: 2.1
Name: morphine-maker
Version: 2.0.2
Summary: Morphine is GUI python framework that empowers you to create a setup.py in approx 4 - 5 mins
Home-page: https://github.com/tbhaxor/morphine
Author: Gurkirat Singh
Author-email: tbhaxor@gmail.com
License: UNKNOWN
Download-URL: https://github.com/tbhaxor/morphine/archive/master.zip
Keywords: morphine,maker,tbhaxor,t3r@byt3,gurkirat,framework
Platform: UNKNOWN
Classifier: Development Status :: 5 - Production/Stable
Classifier: Environment :: X11 Applications :: Qt
Classifier: Intended Audience :: Developers
Classifier: Intended Audience :: End Users/Desktop
Classifier: Programming Language :: Python :: 2
Classifier: Programming Language :: Python :: 2.3
Classifier: Programming Language :: Python :: 2.4
Classifier: Programming Language :: Python :: 2.5
Classifier: Programming Language :: Python :: 2.6
Classifier: Programming Language :: Python :: 2.7
Classifier: Programming Language :: Python :: 3
Classifier: Programming Language :: Python :: 3.0
Classifier: Programming Language :: Python :: 3.1
Classifier: Programming Language :: Python :: 3.2
Classifier: Programming Language :: Python :: 3.4
Classifier: Programming Language :: Python :: 3.5
Classifier: Programming Language :: Python :: 3.6
Classifier: Programming Language :: Python :: 3.7
Classifier: License :: OSI Approved :: MIT License
Requires-Python: >=2, >=3
